myonset/__init__.py
myonset/emgtools.py
myonset/events.py
myonset/latency.py
myonset/utils/__init__.py
myonset/utils/use_mne.py
myonset/utils/use_txt.py
myonset/utils/utilsfunc.py
myonset/viz/__init__.py
myonset/viz/viz_emg.py
myonset-1.1.dist-info/licenses/COPYING
myonset-1.1.dist-info/METADATA
myonset-1.1.dist-info/WHEEL
myonset-1.1.dist-info/top_level.txt
myonset-1.1.dist-info/RECORD
