Metadata-Version: 2.4
Name: myonset
Version: 1.1
Summary: Myonset is a package for detecting EMG burst onset.
Author: Boris Burle
Author-email: Laure Spieser <laure.spieser@univ-amu.fr>
License-Expression: GPL-3.0-or-later
Keywords: EMG,electromyography
Classifier: Programming Language :: Python :: 3
Classifier: Topic :: Scientific/Engineering :: Medical Science Apps.
Classifier: Operating System :: OS Independent
Requires-Python: >=3.6
License-File: COPYING
Requires-Dist: pyqtgraph
Dynamic: license-file
